LICENSE
MANIFEST.in
README.md
setup.cfg
setup.py
nephthys/__init__.py
nephthys.egg-info/PKG-INFO
nephthys.egg-info/SOURCES.txt
nephthys.egg-info/dependency_links.txt
nephthys.egg-info/requires.txt
nephthys.egg-info/top_level.txt
nephthys/clients/__init__.py
nephthys/clients/requests.py
nephthys/filters/__init__.py
nephthys/filters/filter.py
nephthys/filters/message.py
nephthys/filters/requests.py
nephthys/formatters/__init__.py
nephthys/formatters/json.py
nephthys/formatters/pretty.py
tests/test_adapters/test_base.py
tests/test_adapters/test_filter.py
tests/test_clients/__init__.py
tests/test_clients/test_requests.py
tests/test_filters/test_requests.py
tests/test_formatters/test_json.py