Metadata-Version: 2.1
Name: nephthys
Version: 1.0.2
Summary: Advanced Python Logger
Home-page: https://github.com/OvalMoney/Nephthys
Author: Fabio Todaro
Author-email: ft@ovalmoney.com
License: MIT
Platform: UNKNOWN
Classifier: Development Status :: 3 - Alpha
Classifier: Environment :: Console
Classifier: License :: OSI Approved :: MIT License
Classifier: Programming Language :: Python :: 3.6
Classifier: Programming Language :: Python :: 3 :: Only
Classifier: Operating System :: OS Independent
Requires-Python: >=3.6
Provides-Extra: JSON
Provides-Extra: requests
